fitanimate/__init__.py
fitanimate/animator.py
fitanimate/data.py
fitanimate/fitanimate.py
fitanimate/plot.py
fitanimate-0.0.3.dist-info/LICENSE
fitanimate-0.0.3.dist-info/METADATA
fitanimate-0.0.3.dist-info/WHEEL
fitanimate-0.0.3.dist-info/entry_points.txt
fitanimate-0.0.3.dist-info/top_level.txt
fitanimate-0.0.3.dist-info/RECORD
