Metadata-Version: 2.1
Name: fitanimate
Version: 0.0.3
Summary: Fit Animate
Home-page: https://github.com/NickHastings/fitanimate
Author: Nick Hastings
Author-email: nicholaschastings@gmail.com
License: GPLv3
Platform: UNKNOWN
Classifier: Programming Language :: Python :: 3.7
Classifier: License :: OSI Approved :: GNU General Public License v3 (GPLv3)
Classifier: Operating System :: OS Independent
Requires-Python: >=3.7
Requires-Dist: cartopy (>=0.17.0)
Requires-Dist: configargparse (>=0.13.0)
Requires-Dist: fitparse (>=1.2.0)
Requires-Dist: matplotlib (>=3.0.2)
